py5/__init__.py
py5/base.py
py5/bridge.py
py5/color.py
py5/create_font_tool.py
py5/custom_exceptions.py
py5/decorators.py
py5/font.py
py5/graphics.py
py5/image.py
py5/image_conversion.py
py5/keyevent.py
py5/mouseevent.py
py5/object_conversion.py
py5/pmath.py
py5/reference.py
py5/render_helper.py
py5/shader.py
py5/shape.py
py5/shape_conversion.py
py5/sketch.py
py5/spelling.py
py5/surface.py
py5/test.py
py5/utilities.py
py5/vector.py
py5/jars/core.jar
py5/jars/gluegen-rt-main.jar
py5/jars/gluegen-rt.jar
py5/jars/jars.md
py5/jars/jogl-all-main.jar
py5/jars/jogl-all.jar
py5/jars/py5.jar
py5/jars/dxf/bcmail-jdk14-1.38.jar
py5/jars/dxf/bcmail-jdk14-138.jar
py5/jars/dxf/bcprov-jdk14-1.38.jar
py5/jars/dxf/bcprov-jdk14-138.jar
py5/jars/dxf/bctsp-jdk14-1.38.jar
py5/jars/dxf/dxf.jar
py5/jars/dxf/itext.jar
py5/jars/pdf/bcmail-jdk14-1.38.jar
py5/jars/pdf/bcmail-jdk14-138.jar
py5/jars/pdf/bcprov-jdk14-1.38.jar
py5/jars/pdf/bcprov-jdk14-138.jar
py5/jars/pdf/bctsp-jdk14-1.38.jar
py5/jars/pdf/itext.jar
py5/jars/pdf/pdf.jar
py5/jars/svg/batik.jar
py5/jars/svg/svg.jar
py5/mixins/__init__.py
py5/mixins/data.py
py5/mixins/math.py
py5/mixins/pixels.py
py5/mixins/print_tools.py
py5/mixins/threads.py
py5/natives/android-aarch64/libgluegen_rt.so
py5/natives/android-aarch64/libjogl_mobile.so
py5/natives/android-aarch64/libnewt_head.so
py5/natives/linux-aarch64/libgluegen_rt.so
py5/natives/linux-aarch64/libjogl_desktop.so
py5/natives/linux-aarch64/libjogl_mobile.so
py5/natives/linux-aarch64/libnativewindow_awt.so
py5/natives/linux-aarch64/libnativewindow_drm.so
py5/natives/linux-aarch64/libnativewindow_x11.so
py5/natives/linux-aarch64/libnewt_drm.so
py5/natives/linux-aarch64/libnewt_head.so
py5/natives/linux-amd64/libgluegen_rt.so
py5/natives/linux-amd64/libjogl_desktop.so
py5/natives/linux-amd64/libjogl_mobile.so
py5/natives/linux-amd64/libnativewindow_awt.so
py5/natives/linux-amd64/libnativewindow_drm.so
py5/natives/linux-amd64/libnativewindow_x11.so
py5/natives/linux-amd64/libnewt_drm.so
py5-0.10.8a4.dist-info/METADATA
py5-0.10.8a4.dist-info/WHEEL
py5-0.10.8a4.dist-info/entry_points.txt
py5-0.10.8a4.dist-info/licenses/LICENSE
py5-0.10.8a4.dist-info/RECORD
