Metadata-Version: 2.4
Name: py5
Version: 0.10.8a4
Summary: Processing for CPython
Project-URL: Bug Tracker, https://github.com/py5coding/py5generator/issues
Project-URL: Documentation, https://py5coding.org/
Project-URL: Download, https://pypi.org/project/py5
Project-URL: Homepage, https://py5coding.org/
Project-URL: Source Code, https://github.com/py5coding/py5
Author-email: Jim Schmitz <jim@ixora.io>
License-Expression: LGPL-2.1-only
License-File: LICENSE
Keywords: IPython,Jupyter,Processing,Widgets
Classifier: Development Status :: 3 - Alpha
Classifier: Intended Audience :: Developers
Classifier: Intended Audience :: Education
Classifier: Intended Audience :: Science/Research
Classifier: License :: OSI Approved :: GNU Lesser General Public License v2 (LGPLv2)
Classifier: Programming Language :: Java
Classifier: Programming Language :: Python :: 3.9
Classifier: Programming Language :: Python :: 3.10
Classifier: Programming Language :: Python :: 3.11
Classifier: Programming Language :: Python :: 3.12
Classifier: Topic :: Artistic Software
Classifier: Topic :: Multimedia :: Graphics
Requires-Python: >=3.10
Requires-Dist: autopep8>=2.3
Requires-Dist: jpype1>=1.6.0
Requires-Dist: line-profiler>=4.2
Requires-Dist: numpy>=2.2
Requires-Dist: pillow>=11.0
Requires-Dist: pyobjc>=10.1; sys_platform == 'darwin'
Requires-Dist: pywin32>=308; sys_platform == 'win32'
Requires-Dist: requests>=2.32
Requires-Dist: stackprinter>=0.2.12
Provides-Extra: extras
Requires-Dist: colour>=0.1.5; extra == 'extras'
Requires-Dist: matplotlib>=3.10; extra == 'extras'
Requires-Dist: py5jupyter>=0.2.0a0; extra == 'extras'
Requires-Dist: shapely>=2.0; extra == 'extras'
Requires-Dist: svgpathtools>=1.7.0; extra == 'extras'
Requires-Dist: trimesh>=4.6; extra == 'extras'
Provides-Extra: jupyter
Requires-Dist: py5jupyter>=0.2.0a0; extra == 'jupyter'
